pyarmor_runtime_000000/__init__.py
serialkit/__init__.py
serialkit/serialkit.py
serialkit-0.2.0.dist-info/LICENSE
serialkit-0.2.0.dist-info/LICENSE.txt
serialkit-0.2.0.dist-info/METADATA
serialkit-0.2.0.dist-info/WHEEL
serialkit-0.2.0.dist-info/top_level.txt
serialkit-0.2.0.dist-info/RECORD
