Metadata-Version: 2.1
Name: serialkit
Version: 0.2.0
Summary: A Python toolkit for serial and USB communication with dynamic configuration and command support
Home-page: https://github.com/ritesh131/serialkit
Author: Ritesh Bajpai
Author-email: bajpairitesh878@gmail.com
License: Proprietary
Classifier: Programming Language :: Python :: 3
Classifier: License :: Other/Proprietary License
Classifier: Operating System :: OS Independent
Requires-Python: >=3.6
License-File: LICENSE
License-File: LICENSE.txt
Requires-Dist: pyserial>=3.5
